MANIFEST.in
setup.cfg
setup.py
tw/__init__.py
tw.recaptcha.egg-info/PKG-INFO
tw.recaptcha.egg-info/SOURCES.txt
tw.recaptcha.egg-info/dependency_links.txt
tw.recaptcha.egg-info/entry_points.txt
tw.recaptcha.egg-info/namespace_packages.txt
tw.recaptcha.egg-info/not-zip-safe
tw.recaptcha.egg-info/requires.txt
tw.recaptcha.egg-info/top_level.txt
tw/recaptcha/__init__.py
tw/recaptcha/release.py
tw/recaptcha/samples.py
tw/recaptcha/validator.py
tw/recaptcha/widgets.py