Metadata-Version: 1.0
Name: tw.recaptcha
Version: 0.8
Summary: Handy ReCaptcha Toscawidget
Home-page: http://toscawidgets.org/
Author: Christopher Perkins
Author-email: chris@percious.com
License: UNKNOWN
Download-URL: http://toscawidgets.org/download
Keywords: toscawidgets.widgets
Platform: UNKNOWN
Classifier: Development Status :: 3 - Alpha
Classifier: Environment :: Web Environment
Classifier: Environment :: Web Environment :: ToscaWidgets
Classifier: Topic :: Software Development :: Libraries :: Python Modules
Classifier: Topic :: Software Development :: Widget Sets
Classifier: Intended Audience :: Developers
Classifier: Operating System :: OS Independent
Classifier: Programming Language :: Python
